webdavconvert/Converter.py
webdavconvert/Util.py
webdavconvert/Video.py
webdavconvert/WebDAV.py
webdavconvert/__init__.py
webdavconvert/__main__.py
webdavconvert-1.0.0.dist-info/LICENSE
webdavconvert-1.0.0.dist-info/METADATA
webdavconvert-1.0.0.dist-info/WHEEL
webdavconvert-1.0.0.dist-info/top_level.txt
webdavconvert-1.0.0.dist-info/RECORD
