Metadata-Version: 2.1
Name: webdavconvert
Version: 1.0.0
Summary: Convert and transfer video files in WebDAV folders
Home-page: https://github.com/zkmkarlsruhe/pypi-webdavconvert
Author: Christian Lölkes
Author-email: christian.loelkes@gmail.com
License: UNKNOWN
Platform: UNKNOWN
Classifier: Programming Language :: Python :: 3
Classifier: License :: OSI Approved :: MIT License
Classifier: Operating System :: OS Independent
Classifier: Intended Audience :: Education
Requires-Python: >=3.6
Requires-Dist: docopt
Requires-Dist: webdavclient3
